apoor/__init__.py
apoor/data/__init__.py
apoor/data/_data/boston.csv.gz
apoor/data/_data/iris.csv.gz
apoor-1.3.1.dist-info/LICENSE
apoor-1.3.1.dist-info/METADATA
apoor-1.3.1.dist-info/WHEEL
apoor-1.3.1.dist-info/top_level.txt
apoor-1.3.1.dist-info/RECORD
