Metadata-Version: 2.1
Name: apoor
Version: 1.3.1
Summary: A small personal package created to store code and data I often reuse.
Home-page: https://github.com/a-poor/apoor
Author: Austin Poor
Author-email: a-poor@users.noreply.github.com
License: UNKNOWN
Platform: UNKNOWN
Classifier: Programming Language :: Python :: 3.6
Classifier: Programming Language :: Python :: 3.7
Classifier: Programming Language :: Python :: 3.8
Classifier: License :: OSI Approved :: GNU General Public License v3 (GPLv3)
Classifier: Operating System :: OS Independent
Classifier: Development Status :: 5 - Production/Stable
Requires-Python: >=3.6
